qrcode_styled/__init__.py
qrcode_styled/base/__init__.py
qrcode_styled/base/image.py
qrcode_styled/main.py
qrcode_styled/pil/__init__.py
qrcode_styled/pil/figures/__init__.py
qrcode_styled/pil/figures/base.py
qrcode_styled/pil/figures/base.pyi
qrcode_styled/pil/figures/corner.py
qrcode_styled/pil/figures/dot.py
qrcode_styled/pil/image.py
qrcode_styled/svg/__init__.py
qrcode_styled/svg/figures/__init__.py
qrcode_styled/svg/figures/base.py
qrcode_styled/svg/figures/base.pyi
qrcode_styled/svg/figures/corner.py
qrcode_styled/svg/figures/dot.py
qrcode_styled/svg/image.py
qrcode_styled/types.py
qrcode_styled-0.2.2.dist-info/LICENSE
qrcode_styled-0.2.2.dist-info/METADATA
qrcode_styled-0.2.2.dist-info/WHEEL
qrcode_styled-0.2.2.dist-info/RECORD
