Metadata-Version: 2.1
Name: qrcode-styled
Version: 0.2.2
Summary: Python port for kozakdenys/qr-code-styling
Home-page: https://cifrazia.com
License: MIT
Keywords: cifrazia,library,utils,tools,qrcode
Author: Bogdan Parfenov
Author-email: adam.brian.bright@gmail.com
Requires-Python: >=3.10,<4.0
Classifier: Development Status :: 4 - Beta
Classifier: Environment :: Console
Classifier: Framework :: AsyncIO
Classifier: License :: OSI Approved :: MIT License
Classifier: Natural Language :: English
Classifier: Natural Language :: Russian
Classifier: Programming Language :: Python :: 3
Classifier: Programming Language :: Python :: 3.10
Classifier: Programming Language :: Python :: 3.11
Classifier: Programming Language :: Python :: 3.9
Provides-Extra: svg
Requires-Dist: Pillow (>=10.0.0,<11.0.0)
Requires-Dist: lxml (>=4.9.3,<5.0.0) ; extra == "svg"
Requires-Dist: qrcode (>=7.4.2,<8.0.0)
Project-URL: Bug Tracker, https://github.com/AdamBrianBright/qrcode_styled/issues
Project-URL: Contact Author, https://vk.com/adam_bright
Project-URL: Repository, https://github.com/AdamBrianBright/qrcode_styled.git
